// class version 52.0 (52)
// access flags 0x21
public class edu/columbia/cs/psl/test/phosphor/AutoTaintConstructorsObjTagITCase$ExampleWithSinkConstructors implements edu/columbia/cs/psl/phosphor/struct/TaintedWithObjTag {

  // compiled from: AutoTaintConstructorsObjTagITCase.java
  // access flags 0x9
  public static INNERCLASS edu/columbia/cs/psl/test/phosphor/AutoTaintConstructorsObjTagITCase$ExampleWithSinkConstructors edu/columbia/cs/psl/test/phosphor/AutoTaintConstructorsObjTagITCase ExampleWithSinkConstructors

  // access flags 0x1
  public C c

  // access flags 0x81
  public transient [C cs

  // access flags 0x81
  public transient [[C csArr

  // access flags 0x18
  final static J serialVersionUID = 87871184671468939

  // access flags 0x1A
  private final static Ljava/lang/Object; $$PHOSPHOR_REMOVE_SVUID

  // access flags 0x1
  public Ledu/columbia/cs/psl/phosphor/runtime/Taint; PHOSPHOR_TAG

  // access flags 0x1
  public I $$PHOSPHOR_MARK

  // access flags 0x1
  public Ledu/columbia/cs/psl/phosphor/runtime/Taint; cPHOSPHOR_TAG

  // access flags 0x1
  public Ledu/columbia/cs/psl/phosphor/runtime/Taint; csPHOSPHOR_TAG

  // access flags 0x1
  public Ledu/columbia/cs/psl/phosphor/struct/TaggedCharArray; csPHOSPHOR_WRAPPER

  // access flags 0x1
  public Ledu/columbia/cs/psl/phosphor/runtime/Taint; csArrPHOSPHOR_TAG

  // access flags 0x1
  public Ledu/columbia/cs/psl/phosphor/struct/TaggedReferenceArray; csArrPHOSPHOR_WRAPPER

  // access flags 0x9
  public static Ledu/columbia/cs/psl/phosphor/runtime/Taint; serialVersionUIDPHOSPHOR_TAG

  // access flags 0x9
  public static Ledu/columbia/cs/psl/phosphor/runtime/Taint; $$PHOSPHOR_REMOVE_SVUIDPHOSPHOR_TAG

  // access flags 0x1
  public <init>([[C)V
    LDC -856023908
    INVOKESTATIC edu/columbia/cs/psl/phosphor/runtime/PhosphorStackFrame.forMethod (I)Ledu/columbia/cs/psl/phosphor/runtime/PhosphorStackFrame;
    DUP
    INVOKEVIRTUAL edu/columbia/cs/psl/phosphor/runtime/PhosphorStackFrame.getAndClearCleanupFlag ()Z
    ISTORE 2
    ASTORE 3
    INVOKESTATIC edu/columbia/cs/psl/phosphor/runtime/Taint.emptyTaint ()Ledu/columbia/cs/psl/phosphor/runtime/Taint;
    ASTORE 4
    INVOKESTATIC edu/columbia/cs/psl/phosphor/runtime/Taint.emptyTaint ()Ledu/columbia/cs/psl/phosphor/runtime/Taint;
    ASTORE 5
    ALOAD 3
    DUP
    ICONST_0
    INVOKEVIRTUAL edu/columbia/cs/psl/phosphor/runtime/PhosphorStackFrame.getArgTaint (I)Ledu/columbia/cs/psl/phosphor/runtime/Taint;
   L0
    INVOKESTATIC edu/columbia/cs/psl/phosphor/runtime/Taint.emptyTaint ()Ledu/columbia/cs/psl/phosphor/runtime/Taint;
    ASTORE 6
    ASTORE 6
    NOP
    DUP
    ICONST_1
    INVOKEVIRTUAL edu/columbia/cs/psl/phosphor/runtime/PhosphorStackFrame.getArgTaint (I)Ledu/columbia/cs/psl/phosphor/runtime/Taint;
   L1
    INVOKESTATIC edu/columbia/cs/psl/phosphor/runtime/Taint.emptyTaint ()Ledu/columbia/cs/psl/phosphor/runtime/Taint;
    ASTORE 7
    ASTORE 7
    DUP
    ICONST_0
    ALOAD 1
    INVOKEVIRTUAL edu/columbia/cs/psl/phosphor/runtime/PhosphorStackFrame.getArgWrapper (I[Ljava/lang/Object;)Ledu/columbia/cs/psl/phosphor/struct/TaggedReferenceArray;
    CHECKCAST edu/columbia/cs/psl/phosphor/struct/TaggedReferenceArray
    ASTORE 1
    LDC "PhosphorArgTaintIndices=6,7,"
    POP
    POP
   L2
    LINENUMBER 41 L2
    ALOAD 0
    ALOAD 6
    ASTORE 4
    ALOAD 3
    ALOAD 4
    ICONST_0
    INVOKEVIRTUAL edu/columbia/cs/psl/phosphor/runtime/PhosphorStackFrame.setArgTaint (Ledu/columbia/cs/psl/phosphor/runtime/Taint;I)V
    ALOAD 3
    LDC -857263373
    INVOKEVIRTUAL edu/columbia/cs/psl/phosphor/runtime/PhosphorStackFrame.prepareForCall (I)V
    INVOKESPECIAL java/lang/Object.<init> ()V
    GETSTATIC edu/columbia/cs/psl/phosphor/Configuration.autoTainter : Ledu/columbia/cs/psl/phosphor/runtime/TaintSourceWrapper;
    LDC "edu/columbia/cs/psl/test/phosphor/AutoTaintConstructorsObjTagITCase$ExampleWithSinkConstructors.<init>([[C)V"
    LDC "edu/columbia/cs/psl/test/phosphor/AutoTaintConstructorsObjTagITCase$ExampleWithSinkConstructors.<init>([[C)V"
    INVOKEVIRTUAL edu/columbia/cs/psl/phosphor/runtime/TaintSourceWrapper.enteringSink (Ljava/lang/String;Ljava/lang/String;)V
    GETSTATIC edu/columbia/cs/psl/phosphor/Configuration.autoTainter : Ledu/columbia/cs/psl/phosphor/runtime/TaintSourceWrapper;
    SIPUSH 2
    ANEWARRAY java/lang/Object
    DUP
    ICONST_0
    ALOAD 0
    AASTORE
    DUP
    ICONST_1
    ALOAD 1
    AASTORE
    SIPUSH 2
    ANEWARRAY edu/columbia/cs/psl/phosphor/runtime/Taint
    DUP
    ICONST_0
    ALOAD 6
    AASTORE
    DUP
    ICONST_1
    ALOAD 7
    AASTORE
    LDC "edu/columbia/cs/psl/test/phosphor/AutoTaintConstructorsObjTagITCase$ExampleWithSinkConstructors.<init>([[C)V"
    LDC "edu/columbia/cs/psl/test/phosphor/AutoTaintConstructorsObjTagITCase$ExampleWithSinkConstructors.<init>([[C)V"
    INVOKEVIRTUAL edu/columbia/cs/psl/phosphor/runtime/TaintSourceWrapper.checkTaint ([Ljava/lang/Object;[Ledu/columbia/cs/psl/phosphor/runtime/Taint;Ljava/lang/String;Ljava/lang/String;)V
    TRYCATCHBLOCK L3 L4 L4 null
   L3
    ALOAD 3
    INVOKEVIRTUAL edu/columbia/cs/psl/phosphor/runtime/PhosphorStackFrame.getReturnTaint ()Ledu/columbia/cs/psl/phosphor/runtime/Taint;
    POP
   L5
    LINENUMBER 42 L5
    ALOAD 0
    ALOAD 6
    ASTORE 4
    ALOAD 1
    ALOAD 7
    ASTORE 5
    ALOAD 5
    DUP2_X1
    POP2
    DUP_X2
    SWAP
    PUTFIELD edu/columbia/cs/psl/test/phosphor/AutoTaintConstructorsObjTagITCase$ExampleWithSinkConstructors.csArrPHOSPHOR_TAG : Ledu/columbia/cs/psl/phosphor/runtime/Taint;
    PUTFIELD edu/columbia/cs/psl/test/phosphor/AutoTaintConstructorsObjTagITCase$ExampleWithSinkConstructors.csArrPHOSPHOR_WRAPPER : Ledu/columbia/cs/psl/phosphor/struct/TaggedReferenceArray;
   L6
    LINENUMBER 43 L6
    ALOAD 3
    ILOAD 2
    INVOKEVIRTUAL edu/columbia/cs/psl/phosphor/runtime/PhosphorStackFrame.popStackFrameIfNeeded (Z)V
    GETSTATIC edu/columbia/cs/psl/phosphor/Configuration.autoTainter : Ledu/columbia/cs/psl/phosphor/runtime/TaintSourceWrapper;
    LDC "edu/columbia/cs/psl/test/phosphor/AutoTaintConstructorsObjTagITCase$ExampleWithSinkConstructors.<init>([[C)V"
    LDC "edu/columbia/cs/psl/test/phosphor/AutoTaintConstructorsObjTagITCase$ExampleWithSinkConstructors.<init>([[C)V"
    INVOKEVIRTUAL edu/columbia/cs/psl/phosphor/runtime/TaintSourceWrapper.exitingSink (Ljava/lang/String;Ljava/lang/String;)V
    RETURN
   L7
    LOCALVARIABLE this Ledu/columbia/cs/psl/test/phosphor/AutoTaintConstructorsObjTagITCase$ExampleWithSinkConstructors; L2 L7 0
    LOCALVARIABLE this$$PHOSPHORTAG Ledu/columbia/cs/psl/phosphor/runtime/Taint; L0 L7 6
    LOCALVARIABLE csArr$$PHOSPHORTAG Ledu/columbia/cs/psl/phosphor/runtime/Taint; L1 L7 7
    LOCALVARIABLE csArr Ledu/columbia/cs/psl/phosphor/struct/TaggedReferenceArray; L2 L7 1
    LOCALVARIABLE phosphorStackFrame Ledu/columbia/cs/psl/phosphor/runtime/PhosphorStackFrame; L2 L7 3
    LOCALVARIABLE phosphorStackFrameShouldBeClearedAtEnd Z L2 L7 2
    LOCALVARIABLE phosphorStackTaint0 Ledu/columbia/cs/psl/phosphor/runtime/Taint; L2 L7 4
    LOCALVARIABLE phosphorStackTaint1 Ledu/columbia/cs/psl/phosphor/runtime/Taint; L2 L7 5
   L4
   FRAME FULL [] [java/lang/Throwable]
    ASTORE 1
    GETSTATIC edu/columbia/cs/psl/phosphor/Configuration.autoTainter : Ledu/columbia/cs/psl/phosphor/runtime/TaintSourceWrapper;
    LDC "edu/columbia/cs/psl/test/phosphor/AutoTaintConstructorsObjTagITCase$ExampleWithSinkConstructors.<init>([[C)V"
    LDC "edu/columbia/cs/psl/test/phosphor/AutoTaintConstructorsObjTagITCase$ExampleWithSinkConstructors.<init>([[C)V"
    INVOKEVIRTUAL edu/columbia/cs/psl/phosphor/runtime/TaintSourceWrapper.exitingSink (Ljava/lang/String;Ljava/lang/String;)V
    ALOAD 1
    GETSTATIC edu/columbia/cs/psl/phosphor/Configuration.autoTainter : Ledu/columbia/cs/psl/phosphor/runtime/TaintSourceWrapper;
    LDC "edu/columbia/cs/psl/test/phosphor/AutoTaintConstructorsObjTagITCase$ExampleWithSinkConstructors.<init>([[C)V"
    LDC "edu/columbia/cs/psl/test/phosphor/AutoTaintConstructorsObjTagITCase$ExampleWithSinkConstructors.<init>([[C)V"
    INVOKEVIRTUAL edu/columbia/cs/psl/phosphor/runtime/TaintSourceWrapper.exitingSink (Ljava/lang/String;Ljava/lang/String;)V
    ATHROW
    MAXSTACK = 5
    MAXLOCALS = 8

  // access flags 0x1
  public <init>([C)V
    LDC 803669547
    INVOKESTATIC edu/columbia/cs/psl/phosphor/runtime/PhosphorStackFrame.forMethod (I)Ledu/columbia/cs/psl/phosphor/runtime/PhosphorStackFrame;
    DUP
    INVOKEVIRTUAL edu/columbia/cs/psl/phosphor/runtime/PhosphorStackFrame.getAndClearCleanupFlag ()Z
    ISTORE 2
    ASTORE 3
    INVOKESTATIC edu/columbia/cs/psl/phosphor/runtime/Taint.emptyTaint ()Ledu/columbia/cs/psl/phosphor/runtime/Taint;
    ASTORE 4
    INVOKESTATIC edu/columbia/cs/psl/phosphor/runtime/Taint.emptyTaint ()Ledu/columbia/cs/psl/phosphor/runtime/Taint;
    ASTORE 5
    ALOAD 3
    DUP
    ICONST_0
    INVOKEVIRTUAL edu/columbia/cs/psl/phosphor/runtime/PhosphorStackFrame.getArgTaint (I)Ledu/columbia/cs/psl/phosphor/runtime/Taint;
   L0
    INVOKESTATIC edu/columbia/cs/psl/phosphor/runtime/Taint.emptyTaint ()Ledu/columbia/cs/psl/phosphor/runtime/Taint;
    ASTORE 6
    ASTORE 6
    NOP
    DUP
    ICONST_1
    INVOKEVIRTUAL edu/columbia/cs/psl/phosphor/runtime/PhosphorStackFrame.getArgTaint (I)Ledu/columbia/cs/psl/phosphor/runtime/Taint;
   L1
    INVOKESTATIC edu/columbia/cs/psl/phosphor/runtime/Taint.emptyTaint ()Ledu/columbia/cs/psl/phosphor/runtime/Taint;
    ASTORE 7
    ASTORE 7
    DUP
    ICONST_0
    ALOAD 1
    INVOKEVIRTUAL edu/columbia/cs/psl/phosphor/runtime/PhosphorStackFrame.getArgWrapper (I[C)Ledu/columbia/cs/psl/phosphor/struct/TaggedCharArray;
    CHECKCAST edu/columbia/cs/psl/phosphor/struct/TaggedCharArray
    ASTORE 1
    LDC "PhosphorArgTaintIndices=6,7,"
    POP
    POP
   L2
    LINENUMBER 37 L2
    ALOAD 0
    ALOAD 6
    ASTORE 4
    ALOAD 3
    ALOAD 4
    ICONST_0
    INVOKEVIRTUAL edu/columbia/cs/psl/phosphor/runtime/PhosphorStackFrame.setArgTaint (Ledu/columbia/cs/psl/phosphor/runtime/Taint;I)V
    ALOAD 3
    LDC -857263373
    INVOKEVIRTUAL edu/columbia/cs/psl/phosphor/runtime/PhosphorStackFrame.prepareForCall (I)V
    INVOKESPECIAL java/lang/Object.<init> ()V
    GETSTATIC edu/columbia/cs/psl/phosphor/Configuration.autoTainter : Ledu/columbia/cs/psl/phosphor/runtime/TaintSourceWrapper;
    LDC "edu/columbia/cs/psl/test/phosphor/AutoTaintConstructorsObjTagITCase$ExampleWithSinkConstructors.<init>([C)V"
    LDC "edu/columbia/cs/psl/test/phosphor/AutoTaintConstructorsObjTagITCase$ExampleWithSinkConstructors.<init>([C)V"
    INVOKEVIRTUAL edu/columbia/cs/psl/phosphor/runtime/TaintSourceWrapper.enteringSink (Ljava/lang/String;Ljava/lang/String;)V
    GETSTATIC edu/columbia/cs/psl/phosphor/Configuration.autoTainter : Ledu/columbia/cs/psl/phosphor/runtime/TaintSourceWrapper;
    SIPUSH 2
    ANEWARRAY java/lang/Object
    DUP
    ICONST_0
    ALOAD 0
    AASTORE
    DUP
    ICONST_1
    ALOAD 1
    AASTORE
    SIPUSH 2
    ANEWARRAY edu/columbia/cs/psl/phosphor/runtime/Taint
    DUP
    ICONST_0
    ALOAD 6
    AASTORE
    DUP
    ICONST_1
    ALOAD 7
    AASTORE
    LDC "edu/columbia/cs/psl/test/phosphor/AutoTaintConstructorsObjTagITCase$ExampleWithSinkConstructors.<init>([C)V"
    LDC "edu/columbia/cs/psl/test/phosphor/AutoTaintConstructorsObjTagITCase$ExampleWithSinkConstructors.<init>([C)V"
    INVOKEVIRTUAL edu/columbia/cs/psl/phosphor/runtime/TaintSourceWrapper.checkTaint ([Ljava/lang/Object;[Ledu/columbia/cs/psl/phosphor/runtime/Taint;Ljava/lang/String;Ljava/lang/String;)V
    TRYCATCHBLOCK L3 L4 L4 null
   L3
    ALOAD 3
    INVOKEVIRTUAL edu/columbia/cs/psl/phosphor/runtime/PhosphorStackFrame.getReturnTaint ()Ledu/columbia/cs/psl/phosphor/runtime/Taint;
    POP
   L5
    LINENUMBER 38 L5
    ALOAD 0
    ALOAD 6
    ASTORE 4
    ALOAD 1
    ALOAD 7
    ASTORE 5
    ALOAD 5
    DUP2_X1
    POP2
    DUP_X2
    SWAP
    PUTFIELD edu/columbia/cs/psl/test/phosphor/AutoTaintConstructorsObjTagITCase$ExampleWithSinkConstructors.csPHOSPHOR_TAG : Ledu/columbia/cs/psl/phosphor/runtime/Taint;
    DUP2
    INVOKESTATIC edu/columbia/cs/psl/phosphor/struct/TaggedCharArray.unwrap (Ledu/columbia/cs/psl/phosphor/struct/TaggedCharArray;)[C
    PUTFIELD edu/columbia/cs/psl/test/phosphor/AutoTaintConstructorsObjTagITCase$ExampleWithSinkConstructors.cs : [C
    PUTFIELD edu/columbia/cs/psl/test/phosphor/AutoTaintConstructorsObjTagITCase$ExampleWithSinkConstructors.csPHOSPHOR_WRAPPER : Ledu/columbia/cs/psl/phosphor/struct/TaggedCharArray;
   L6
    LINENUMBER 39 L6
    ALOAD 3
    ILOAD 2
    INVOKEVIRTUAL edu/columbia/cs/psl/phosphor/runtime/PhosphorStackFrame.popStackFrameIfNeeded (Z)V
    GETSTATIC edu/columbia/cs/psl/phosphor/Configuration.autoTainter : Ledu/columbia/cs/psl/phosphor/runtime/TaintSourceWrapper;
    LDC "edu/columbia/cs/psl/test/phosphor/AutoTaintConstructorsObjTagITCase$ExampleWithSinkConstructors.<init>([C)V"
    LDC "edu/columbia/cs/psl/test/phosphor/AutoTaintConstructorsObjTagITCase$ExampleWithSinkConstructors.<init>([C)V"
    INVOKEVIRTUAL edu/columbia/cs/psl/phosphor/runtime/TaintSourceWrapper.exitingSink (Ljava/lang/String;Ljava/lang/String;)V
    RETURN
   L7
    LOCALVARIABLE this Ledu/columbia/cs/psl/test/phosphor/AutoTaintConstructorsObjTagITCase$ExampleWithSinkConstructors; L2 L7 0
    LOCALVARIABLE cs$$PHOSPHORTAG Ledu/columbia/cs/psl/phosphor/runtime/Taint; L1 L7 7
    LOCALVARIABLE this$$PHOSPHORTAG Ledu/columbia/cs/psl/phosphor/runtime/Taint; L0 L7 6
    LOCALVARIABLE cs [C L2 L7 1
    LOCALVARIABLE phosphorStackFrame Ledu/columbia/cs/psl/phosphor/runtime/PhosphorStackFrame; L2 L7 3
    LOCALVARIABLE phosphorStackFrameShouldBeClearedAtEnd Z L2 L7 2
    LOCALVARIABLE phosphorStackTaint0 Ledu/columbia/cs/psl/phosphor/runtime/Taint; L2 L7 4
    LOCALVARIABLE phosphorStackTaint1 Ledu/columbia/cs/psl/phosphor/runtime/Taint; L2 L7 5
   L4
   FRAME FULL [] [java/lang/Throwable]
    ASTORE 1
    GETSTATIC edu/columbia/cs/psl/phosphor/Configuration.autoTainter : Ledu/columbia/cs/psl/phosphor/runtime/TaintSourceWrapper;
    LDC "edu/columbia/cs/psl/test/phosphor/AutoTaintConstructorsObjTagITCase$ExampleWithSinkConstructors.<init>([C)V"
    LDC "edu/columbia/cs/psl/test/phosphor/AutoTaintConstructorsObjTagITCase$ExampleWithSinkConstructors.<init>([C)V"
    INVOKEVIRTUAL edu/columbia/cs/psl/phosphor/runtime/TaintSourceWrapper.exitingSink (Ljava/lang/String;Ljava/lang/String;)V
    ALOAD 1
    GETSTATIC edu/columbia/cs/psl/phosphor/Configuration.autoTainter : Ledu/columbia/cs/psl/phosphor/runtime/TaintSourceWrapper;
    LDC "edu/columbia/cs/psl/test/phosphor/AutoTaintConstructorsObjTagITCase$ExampleWithSinkConstructors.<init>([C)V"
    LDC "edu/columbia/cs/psl/test/phosphor/AutoTaintConstructorsObjTagITCase$ExampleWithSinkConstructors.<init>([C)V"
    INVOKEVIRTUAL edu/columbia/cs/psl/phosphor/runtime/TaintSourceWrapper.exitingSink (Ljava/lang/String;Ljava/lang/String;)V
    ATHROW
    MAXSTACK = 5
    MAXLOCALS = 8

  // access flags 0x1
  public <init>(C)V
    LDC -805359940
    INVOKESTATIC edu/columbia/cs/psl/phosphor/runtime/PhosphorStackFrame.forMethod (I)Ledu/columbia/cs/psl/phosphor/runtime/PhosphorStackFrame;
    DUP
    INVOKEVIRTUAL edu/columbia/cs/psl/phosphor/runtime/PhosphorStackFrame.getAndClearCleanupFlag ()Z
    ISTORE 2
    ASTORE 3
    INVOKESTATIC edu/columbia/cs/psl/phosphor/runtime/Taint.emptyTaint ()Ledu/columbia/cs/psl/phosphor/runtime/Taint;
    ASTORE 4
    INVOKESTATIC edu/columbia/cs/psl/phosphor/runtime/Taint.emptyTaint ()Ledu/columbia/cs/psl/phosphor/runtime/Taint;
    ASTORE 5
    ALOAD 3
    DUP
    ICONST_0
    INVOKEVIRTUAL edu/columbia/cs/psl/phosphor/runtime/PhosphorStackFrame.getArgTaint (I)Ledu/columbia/cs/psl/phosphor/runtime/Taint;
   L0
    INVOKESTATIC edu/columbia/cs/psl/phosphor/runtime/Taint.emptyTaint ()Ledu/columbia/cs/psl/phosphor/runtime/Taint;
    ASTORE 6
    ASTORE 6
    NOP
    DUP
    ICONST_1
    INVOKEVIRTUAL edu/columbia/cs/psl/phosphor/runtime/PhosphorStackFrame.getArgTaint (I)Ledu/columbia/cs/psl/phosphor/runtime/Taint;
   L1
    INVOKESTATIC edu/columbia/cs/psl/phosphor/runtime/Taint.emptyTaint ()Ledu/columbia/cs/psl/phosphor/runtime/Taint;
    ASTORE 7
    ASTORE 7
    LDC "PhosphorArgTaintIndices=6,7,"
    POP
    POP
   L2
    LINENUMBER 33 L2
    ALOAD 0
    ALOAD 6
    ASTORE 4
    ALOAD 3
    ALOAD 4
    ICONST_0
    INVOKEVIRTUAL edu/columbia/cs/psl/phosphor/runtime/PhosphorStackFrame.setArgTaint (Ledu/columbia/cs/psl/phosphor/runtime/Taint;I)V
    ALOAD 3
    LDC -857263373
    INVOKEVIRTUAL edu/columbia/cs/psl/phosphor/runtime/PhosphorStackFrame.prepareForCall (I)V
    INVOKESPECIAL java/lang/Object.<init> ()V
    GETSTATIC edu/columbia/cs/psl/phosphor/Configuration.autoTainter : Ledu/columbia/cs/psl/phosphor/runtime/TaintSourceWrapper;
    LDC "edu/columbia/cs/psl/test/phosphor/AutoTaintConstructorsObjTagITCase$ExampleWithSinkConstructors.<init>(C)V"
    LDC "edu/columbia/cs/psl/test/phosphor/AutoTaintConstructorsObjTagITCase$ExampleWithSinkConstructors.<init>(C)V"
    INVOKEVIRTUAL edu/columbia/cs/psl/phosphor/runtime/TaintSourceWrapper.enteringSink (Ljava/lang/String;Ljava/lang/String;)V
    GETSTATIC edu/columbia/cs/psl/phosphor/Configuration.autoTainter : Ledu/columbia/cs/psl/phosphor/runtime/TaintSourceWrapper;
    SIPUSH 2
    ANEWARRAY java/lang/Object
    DUP
    ICONST_0
    ALOAD 0
    AASTORE
    DUP
    ICONST_1
    ILOAD 1
    NEW java/lang/Character
    DUP_X1
    SWAP
    INVOKESPECIAL java/lang/Character.<init> (C)V
    AASTORE
    SIPUSH 2
    ANEWARRAY edu/columbia/cs/psl/phosphor/runtime/Taint
    DUP
    ICONST_0
    ALOAD 6
    AASTORE
    DUP
    ICONST_1
    ALOAD 7
    AASTORE
    LDC "edu/columbia/cs/psl/test/phosphor/AutoTaintConstructorsObjTagITCase$ExampleWithSinkConstructors.<init>(C)V"
    LDC "edu/columbia/cs/psl/test/phosphor/AutoTaintConstructorsObjTagITCase$ExampleWithSinkConstructors.<init>(C)V"
    INVOKEVIRTUAL edu/columbia/cs/psl/phosphor/runtime/TaintSourceWrapper.checkTaint ([Ljava/lang/Object;[Ledu/columbia/cs/psl/phosphor/runtime/Taint;Ljava/lang/String;Ljava/lang/String;)V
    TRYCATCHBLOCK L3 L4 L4 null
   L3
    ALOAD 3
    INVOKEVIRTUAL edu/columbia/cs/psl/phosphor/runtime/PhosphorStackFrame.getReturnTaint ()Ledu/columbia/cs/psl/phosphor/runtime/Taint;
    POP
   L5
    LINENUMBER 34 L5
    ALOAD 0
    ALOAD 6
    ASTORE 4
    ILOAD 1
    ALOAD 7
    ASTORE 5
    ALOAD 5
    DUP2_X1
    POP2
    DUP_X2
    SWAP
    PUTFIELD edu/columbia/cs/psl/test/phosphor/AutoTaintConstructorsObjTagITCase$ExampleWithSinkConstructors.cPHOSPHOR_TAG : Ledu/columbia/cs/psl/phosphor/runtime/Taint;
    PUTFIELD edu/columbia/cs/psl/test/phosphor/AutoTaintConstructorsObjTagITCase$ExampleWithSinkConstructors.c : C
   L6
    LINENUMBER 35 L6
    ALOAD 3
    ILOAD 2
    INVOKEVIRTUAL edu/columbia/cs/psl/phosphor/runtime/PhosphorStackFrame.popStackFrameIfNeeded (Z)V
    GETSTATIC edu/columbia/cs/psl/phosphor/Configuration.autoTainter : Ledu/columbia/cs/psl/phosphor/runtime/TaintSourceWrapper;
    LDC "edu/columbia/cs/psl/test/phosphor/AutoTaintConstructorsObjTagITCase$ExampleWithSinkConstructors.<init>(C)V"
    LDC "edu/columbia/cs/psl/test/phosphor/AutoTaintConstructorsObjTagITCase$ExampleWithSinkConstructors.<init>(C)V"
    INVOKEVIRTUAL edu/columbia/cs/psl/phosphor/runtime/TaintSourceWrapper.exitingSink (Ljava/lang/String;Ljava/lang/String;)V
    RETURN
   L7
    LOCALVARIABLE this Ledu/columbia/cs/psl/test/phosphor/AutoTaintConstructorsObjTagITCase$ExampleWithSinkConstructors; L2 L7 0
    LOCALVARIABLE this$$PHOSPHORTAG Ledu/columbia/cs/psl/phosphor/runtime/Taint; L0 L7 6
    LOCALVARIABLE c$$PHOSPHORTAG Ledu/columbia/cs/psl/phosphor/runtime/Taint; L1 L7 7
    LOCALVARIABLE c C L2 L7 1
    LOCALVARIABLE phosphorStackFrame Ledu/columbia/cs/psl/phosphor/runtime/PhosphorStackFrame; L2 L7 3
    LOCALVARIABLE phosphorStackFrameShouldBeClearedAtEnd Z L2 L7 2
    LOCALVARIABLE phosphorStackTaint0 Ledu/columbia/cs/psl/phosphor/runtime/Taint; L2 L7 4
    LOCALVARIABLE phosphorStackTaint1 Ledu/columbia/cs/psl/phosphor/runtime/Taint; L2 L7 5
   L4
   FRAME FULL [] [java/lang/Throwable]
    ASTORE 1
    GETSTATIC edu/columbia/cs/psl/phosphor/Configuration.autoTainter : Ledu/columbia/cs/psl/phosphor/runtime/TaintSourceWrapper;
    LDC "edu/columbia/cs/psl/test/phosphor/AutoTaintConstructorsObjTagITCase$ExampleWithSinkConstructors.<init>(C)V"
    LDC "edu/columbia/cs/psl/test/phosphor/AutoTaintConstructorsObjTagITCase$ExampleWithSinkConstructors.<init>(C)V"
    INVOKEVIRTUAL edu/columbia/cs/psl/phosphor/runtime/TaintSourceWrapper.exitingSink (Ljava/lang/String;Ljava/lang/String;)V
    ALOAD 1
    GETSTATIC edu/columbia/cs/psl/phosphor/Configuration.autoTainter : Ledu/columbia/cs/psl/phosphor/runtime/TaintSourceWrapper;
    LDC "edu/columbia/cs/psl/test/phosphor/AutoTaintConstructorsObjTagITCase$ExampleWithSinkConstructors.<init>(C)V"
    LDC "edu/columbia/cs/psl/test/phosphor/AutoTaintConstructorsObjTagITCase$ExampleWithSinkConstructors.<init>(C)V"
    INVOKEVIRTUAL edu/columbia/cs/psl/phosphor/runtime/TaintSourceWrapper.exitingSink (Ljava/lang/String;Ljava/lang/String;)V
    ATHROW
    MAXSTACK = 5
    MAXLOCALS = 8

  // access flags 0x8
  static <clinit>()V
    LDC Ledu/columbia/cs/psl/test/phosphor/AutoTaintConstructorsObjTagITCase$ExampleWithSinkConstructors;.class
    INVOKESTATIC edu/columbia/cs/psl/phosphor/SourceSinkTransformer.retransform (Ljava/lang/Class;)V
    RETURN
    MAXSTACK = 1
    MAXLOCALS = 0

  // access flags 0x1001
  public synthetic getPHOSPHOR_TAG()Ljava/lang/Object;
    ALOAD 0
    GETFIELD edu/columbia/cs/psl/test/phosphor/AutoTaintConstructorsObjTagITCase$ExampleWithSinkConstructors.PHOSPHOR_TAG : Ledu/columbia/cs/psl/phosphor/runtime/Taint;
    ARETURN
    MAXSTACK = 1
    MAXLOCALS = 1

  // access flags 0x1001
  public synthetic setPHOSPHOR_TAG(Ljava/lang/Object;)V
    ALOAD 0
    ALOAD 1
    CHECKCAST edu/columbia/cs/psl/phosphor/runtime/Taint
    PUTFIELD edu/columbia/cs/psl/test/phosphor/AutoTaintConstructorsObjTagITCase$ExampleWithSinkConstructors.PHOSPHOR_TAG : Ledu/columbia/cs/psl/phosphor/runtime/Taint;
    RETURN
    MAXSTACK = 2
    MAXLOCALS = 2
}
// class version 52.0 (52)
// access flags 0x21
public class edu/columbia/cs/psl/test/phosphor/AutoTaintConstructorsObjTagITCase$ExampleWithSinkConstructors implements edu/columbia/cs/psl/phosphor/struct/TaintedWithObjTag {

  // compiled from: AutoTaintConstructorsObjTagITCase.java
  // access flags 0x9
  public static INNERCLASS edu/columbia/cs/psl/test/phosphor/AutoTaintConstructorsObjTagITCase$ExampleWithSinkConstructors edu/columbia/cs/psl/test/phosphor/AutoTaintConstructorsObjTagITCase ExampleWithSinkConstructors

  // access flags 0x1
  public C c

  // access flags 0x81
  public transient [C cs

  // access flags 0x81
  public transient [[C csArr

  // access flags 0x18
  final static J serialVersionUID = 87871184671468939

  // access flags 0x1A
  private final static Ljava/lang/Object; $$PHOSPHOR_REMOVE_SVUID

  // access flags 0x1
  public Ledu/columbia/cs/psl/phosphor/runtime/Taint; PHOSPHOR_TAG

  // access flags 0x1
  public I $$PHOSPHOR_MARK

  // access flags 0x1
  public Ledu/columbia/cs/psl/phosphor/runtime/Taint; cPHOSPHOR_TAG

  // access flags 0x1
  public Ledu/columbia/cs/psl/phosphor/runtime/Taint; csPHOSPHOR_TAG

  // access flags 0x1
  public Ledu/columbia/cs/psl/phosphor/struct/TaggedCharArray; csPHOSPHOR_WRAPPER

  // access flags 0x1
  public Ledu/columbia/cs/psl/phosphor/runtime/Taint; csArrPHOSPHOR_TAG

  // access flags 0x1
  public Ledu/columbia/cs/psl/phosphor/struct/TaggedReferenceArray; csArrPHOSPHOR_WRAPPER

  // access flags 0x9
  public static Ledu/columbia/cs/psl/phosphor/runtime/Taint; serialVersionUIDPHOSPHOR_TAG

  // access flags 0x9
  public static Ledu/columbia/cs/psl/phosphor/runtime/Taint; $$PHOSPHOR_REMOVE_SVUIDPHOSPHOR_TAG

  // access flags 0x1
  public <init>([[C)V
    LDC -856023908
    INVOKESTATIC edu/columbia/cs/psl/phosphor/runtime/PhosphorStackFrame.forMethod (I)Ledu/columbia/cs/psl/phosphor/runtime/PhosphorStackFrame;
    DUP
    INVOKEVIRTUAL edu/columbia/cs/psl/phosphor/runtime/PhosphorStackFrame.getAndClearCleanupFlag ()Z
    ISTORE 2
    ASTORE 3
    INVOKESTATIC edu/columbia/cs/psl/phosphor/runtime/Taint.emptyTaint ()Ledu/columbia/cs/psl/phosphor/runtime/Taint;
    ASTORE 4
    INVOKESTATIC edu/columbia/cs/psl/phosphor/runtime/Taint.emptyTaint ()Ledu/columbia/cs/psl/phosphor/runtime/Taint;
    ASTORE 5
    ALOAD 3
    DUP
    ICONST_0
    INVOKEVIRTUAL edu/columbia/cs/psl/phosphor/runtime/PhosphorStackFrame.getArgTaint (I)Ledu/columbia/cs/psl/phosphor/runtime/Taint;
   L0
    INVOKESTATIC edu/columbia/cs/psl/phosphor/runtime/Taint.emptyTaint ()Ledu/columbia/cs/psl/phosphor/runtime/Taint;
    ASTORE 6
    ASTORE 6
    NOP
    DUP
    ICONST_1
    INVOKEVIRTUAL edu/columbia/cs/psl/phosphor/runtime/PhosphorStackFrame.getArgTaint (I)Ledu/columbia/cs/psl/phosphor/runtime/Taint;
   L1
    INVOKESTATIC edu/columbia/cs/psl/phosphor/runtime/Taint.emptyTaint ()Ledu/columbia/cs/psl/phosphor/runtime/Taint;
    ASTORE 7
    ASTORE 7
    DUP
    ICONST_0
    ALOAD 1
    INVOKEVIRTUAL edu/columbia/cs/psl/phosphor/runtime/PhosphorStackFrame.getArgWrapper (I[Ljava/lang/Object;)Ledu/columbia/cs/psl/phosphor/struct/TaggedReferenceArray;
    CHECKCAST edu/columbia/cs/psl/phosphor/struct/TaggedReferenceArray
    ASTORE 1
    LDC "PhosphorArgTaintIndices=6,7,"
    POP
    POP
   L2
    LINENUMBER 41 L2
    ALOAD 0
    ALOAD 6
    ASTORE 4
    ALOAD 3
    ALOAD 4
    ICONST_0
    INVOKEVIRTUAL edu/columbia/cs/psl/phosphor/runtime/PhosphorStackFrame.setArgTaint (Ledu/columbia/cs/psl/phosphor/runtime/Taint;I)V
    ALOAD 3
    LDC -857263373
    INVOKEVIRTUAL edu/columbia/cs/psl/phosphor/runtime/PhosphorStackFrame.prepareForCall (I)V
    INVOKESPECIAL java/lang/Object.<init> ()V
    GETSTATIC edu/columbia/cs/psl/phosphor/Configuration.autoTainter : Ledu/columbia/cs/psl/phosphor/runtime/TaintSourceWrapper;
    LDC "edu/columbia/cs/psl/test/phosphor/AutoTaintConstructorsObjTagITCase$ExampleWithSinkConstructors.<init>([[C)V"
    LDC "edu/columbia/cs/psl/test/phosphor/AutoTaintConstructorsObjTagITCase$ExampleWithSinkConstructors.<init>([[C)V"
    INVOKEVIRTUAL edu/columbia/cs/psl/phosphor/runtime/TaintSourceWrapper.enteringSink (Ljava/lang/String;Ljava/lang/String;)V
    GETSTATIC edu/columbia/cs/psl/phosphor/Configuration.autoTainter : Ledu/columbia/cs/psl/phosphor/runtime/TaintSourceWrapper;
    SIPUSH 2
    ANEWARRAY java/lang/Object
    DUP
    ICONST_0
    ALOAD 0
    AASTORE
    DUP
    ICONST_1
    ALOAD 1
    AASTORE
    SIPUSH 2
    ANEWARRAY edu/columbia/cs/psl/phosphor/runtime/Taint
    DUP
    ICONST_0
    ALOAD 6
    AASTORE
    DUP
    ICONST_1
    ALOAD 7
    AASTORE
    LDC "edu/columbia/cs/psl/test/phosphor/AutoTaintConstructorsObjTagITCase$ExampleWithSinkConstructors.<init>([[C)V"
    LDC "edu/columbia/cs/psl/test/phosphor/AutoTaintConstructorsObjTagITCase$ExampleWithSinkConstructors.<init>([[C)V"
    INVOKEVIRTUAL edu/columbia/cs/psl/phosphor/runtime/TaintSourceWrapper.checkTaint ([Ljava/lang/Object;[Ledu/columbia/cs/psl/phosphor/runtime/Taint;Ljava/lang/String;Ljava/lang/String;)V
    TRYCATCHBLOCK L3 L4 L4 null
   L3
    ALOAD 3
    INVOKEVIRTUAL edu/columbia/cs/psl/phosphor/runtime/PhosphorStackFrame.getReturnTaint ()Ledu/columbia/cs/psl/phosphor/runtime/Taint;
    POP
   L5
    LINENUMBER 42 L5
    ALOAD 0
    ALOAD 6
    ASTORE 4
    ALOAD 1
    ALOAD 7
    ASTORE 5
    ALOAD 5
    DUP2_X1
    POP2
    DUP_X2
    SWAP
    PUTFIELD edu/columbia/cs/psl/test/phosphor/AutoTaintConstructorsObjTagITCase$ExampleWithSinkConstructors.csArrPHOSPHOR_TAG : Ledu/columbia/cs/psl/phosphor/runtime/Taint;
    PUTFIELD edu/columbia/cs/psl/test/phosphor/AutoTaintConstructorsObjTagITCase$ExampleWithSinkConstructors.csArrPHOSPHOR_WRAPPER : Ledu/columbia/cs/psl/phosphor/struct/TaggedReferenceArray;
   L6
    LINENUMBER 43 L6
    ALOAD 3
    ILOAD 2
    INVOKEVIRTUAL edu/columbia/cs/psl/phosphor/runtime/PhosphorStackFrame.popStackFrameIfNeeded (Z)V
    GETSTATIC edu/columbia/cs/psl/phosphor/Configuration.autoTainter : Ledu/columbia/cs/psl/phosphor/runtime/TaintSourceWrapper;
    LDC "edu/columbia/cs/psl/test/phosphor/AutoTaintConstructorsObjTagITCase$ExampleWithSinkConstructors.<init>([[C)V"
    LDC "edu/columbia/cs/psl/test/phosphor/AutoTaintConstructorsObjTagITCase$ExampleWithSinkConstructors.<init>([[C)V"
    INVOKEVIRTUAL edu/columbia/cs/psl/phosphor/runtime/TaintSourceWrapper.exitingSink (Ljava/lang/String;Ljava/lang/String;)V
    RETURN
   L7
    LOCALVARIABLE this Ledu/columbia/cs/psl/test/phosphor/AutoTaintConstructorsObjTagITCase$ExampleWithSinkConstructors; L2 L7 0
    LOCALVARIABLE this$$PHOSPHORTAG Ledu/columbia/cs/psl/phosphor/runtime/Taint; L0 L7 6
    LOCALVARIABLE csArr$$PHOSPHORTAG Ledu/columbia/cs/psl/phosphor/runtime/Taint; L1 L7 7
    LOCALVARIABLE csArr Ledu/columbia/cs/psl/phosphor/struct/TaggedReferenceArray; L2 L7 1
    LOCALVARIABLE phosphorStackFrame Ledu/columbia/cs/psl/phosphor/runtime/PhosphorStackFrame; L2 L7 3
    LOCALVARIABLE phosphorStackFrameShouldBeClearedAtEnd Z L2 L7 2
    LOCALVARIABLE phosphorStackTaint0 Ledu/columbia/cs/psl/phosphor/runtime/Taint; L2 L7 4
    LOCALVARIABLE phosphorStackTaint1 Ledu/columbia/cs/psl/phosphor/runtime/Taint; L2 L7 5
   L4
   FRAME FULL [] [java/lang/Throwable]
    ASTORE 1
    GETSTATIC edu/columbia/cs/psl/phosphor/Configuration.autoTainter : Ledu/columbia/cs/psl/phosphor/runtime/TaintSourceWrapper;
    LDC "edu/columbia/cs/psl/test/phosphor/AutoTaintConstructorsObjTagITCase$ExampleWithSinkConstructors.<init>([[C)V"
    LDC "edu/columbia/cs/psl/test/phosphor/AutoTaintConstructorsObjTagITCase$ExampleWithSinkConstructors.<init>([[C)V"
    INVOKEVIRTUAL edu/columbia/cs/psl/phosphor/runtime/TaintSourceWrapper.exitingSink (Ljava/lang/String;Ljava/lang/String;)V
    ALOAD 1
    GETSTATIC edu/columbia/cs/psl/phosphor/Configuration.autoTainter : Ledu/columbia/cs/psl/phosphor/runtime/TaintSourceWrapper;
    LDC "edu/columbia/cs/psl/test/phosphor/AutoTaintConstructorsObjTagITCase$ExampleWithSinkConstructors.<init>([[C)V"
    LDC "edu/columbia/cs/psl/test/phosphor/AutoTaintConstructorsObjTagITCase$ExampleWithSinkConstructors.<init>([[C)V"
    INVOKEVIRTUAL edu/columbia/cs/psl/phosphor/runtime/TaintSourceWrapper.exitingSink (Ljava/lang/String;Ljava/lang/String;)V
    ATHROW
    MAXSTACK = 5
    MAXLOCALS = 8

  // access flags 0x1
  public <init>([C)V
    LDC 803669547
    INVOKESTATIC edu/columbia/cs/psl/phosphor/runtime/PhosphorStackFrame.forMethod (I)Ledu/columbia/cs/psl/phosphor/runtime/PhosphorStackFrame;
    DUP
    INVOKEVIRTUAL edu/columbia/cs/psl/phosphor/runtime/PhosphorStackFrame.getAndClearCleanupFlag ()Z
    ISTORE 2
    ASTORE 3
    INVOKESTATIC edu/columbia/cs/psl/phosphor/runtime/Taint.emptyTaint ()Ledu/columbia/cs/psl/phosphor/runtime/Taint;
    ASTORE 4
    INVOKESTATIC edu/columbia/cs/psl/phosphor/runtime/Taint.emptyTaint ()Ledu/columbia/cs/psl/phosphor/runtime/Taint;
    ASTORE 5
    ALOAD 3
    DUP
    ICONST_0
    INVOKEVIRTUAL edu/columbia/cs/psl/phosphor/runtime/PhosphorStackFrame.getArgTaint (I)Ledu/columbia/cs/psl/phosphor/runtime/Taint;
   L0
    INVOKESTATIC edu/columbia/cs/psl/phosphor/runtime/Taint.emptyTaint ()Ledu/columbia/cs/psl/phosphor/runtime/Taint;
    ASTORE 6
    ASTORE 6
    NOP
    DUP
    ICONST_1
    INVOKEVIRTUAL edu/columbia/cs/psl/phosphor/runtime/PhosphorStackFrame.getArgTaint (I)Ledu/columbia/cs/psl/phosphor/runtime/Taint;
   L1
    INVOKESTATIC edu/columbia/cs/psl/phosphor/runtime/Taint.emptyTaint ()Ledu/columbia/cs/psl/phosphor/runtime/Taint;
    ASTORE 7
    ASTORE 7
    DUP
    ICONST_0
    ALOAD 1
    INVOKEVIRTUAL edu/columbia/cs/psl/phosphor/runtime/PhosphorStackFrame.getArgWrapper (I[C)Ledu/columbia/cs/psl/phosphor/struct/TaggedCharArray;
    CHECKCAST edu/columbia/cs/psl/phosphor/struct/TaggedCharArray
    ASTORE 1
    LDC "PhosphorArgTaintIndices=6,7,"
    POP
    POP
   L2
    LINENUMBER 37 L2
    ALOAD 0
    ALOAD 6
    ASTORE 4
    ALOAD 3
    ALOAD 4
    ICONST_0
    INVOKEVIRTUAL edu/columbia/cs/psl/phosphor/runtime/PhosphorStackFrame.setArgTaint (Ledu/columbia/cs/psl/phosphor/runtime/Taint;I)V
    ALOAD 3
    LDC -857263373
    INVOKEVIRTUAL edu/columbia/cs/psl/phosphor/runtime/PhosphorStackFrame.prepareForCall (I)V
    INVOKESPECIAL java/lang/Object.<init> ()V
    GETSTATIC edu/columbia/cs/psl/phosphor/Configuration.autoTainter : Ledu/columbia/cs/psl/phosphor/runtime/TaintSourceWrapper;
    LDC "edu/columbia/cs/psl/test/phosphor/AutoTaintConstructorsObjTagITCase$ExampleWithSinkConstructors.<init>([C)V"
    LDC "edu/columbia/cs/psl/test/phosphor/AutoTaintConstructorsObjTagITCase$ExampleWithSinkConstructors.<init>([C)V"
    INVOKEVIRTUAL edu/columbia/cs/psl/phosphor/runtime/TaintSourceWrapper.enteringSink (Ljava/lang/String;Ljava/lang/String;)V
    GETSTATIC edu/columbia/cs/psl/phosphor/Configuration.autoTainter : Ledu/columbia/cs/psl/phosphor/runtime/TaintSourceWrapper;
    SIPUSH 2
    ANEWARRAY java/lang/Object
    DUP
    ICONST_0
    ALOAD 0
    AASTORE
    DUP
    ICONST_1
    ALOAD 1
    AASTORE
    SIPUSH 2
    ANEWARRAY edu/columbia/cs/psl/phosphor/runtime/Taint
    DUP
    ICONST_0
    ALOAD 6
    AASTORE
    DUP
    ICONST_1
    ALOAD 7
    AASTORE
    LDC "edu/columbia/cs/psl/test/phosphor/AutoTaintConstructorsObjTagITCase$ExampleWithSinkConstructors.<init>([C)V"
    LDC "edu/columbia/cs/psl/test/phosphor/AutoTaintConstructorsObjTagITCase$ExampleWithSinkConstructors.<init>([C)V"
    INVOKEVIRTUAL edu/columbia/cs/psl/phosphor/runtime/TaintSourceWrapper.checkTaint ([Ljava/lang/Object;[Ledu/columbia/cs/psl/phosphor/runtime/Taint;Ljava/lang/String;Ljava/lang/String;)V
    TRYCATCHBLOCK L3 L4 L4 null
   L3
    ALOAD 3
    INVOKEVIRTUAL edu/columbia/cs/psl/phosphor/runtime/PhosphorStackFrame.getReturnTaint ()Ledu/columbia/cs/psl/phosphor/runtime/Taint;
    POP
   L5
    LINENUMBER 38 L5
    ALOAD 0
    ALOAD 6
    ASTORE 4
    ALOAD 1
    ALOAD 7
    ASTORE 5
    ALOAD 5
    DUP2_X1
    POP2
    DUP_X2
    SWAP
    PUTFIELD edu/columbia/cs/psl/test/phosphor/AutoTaintConstructorsObjTagITCase$ExampleWithSinkConstructors.csPHOSPHOR_TAG : Ledu/columbia/cs/psl/phosphor/runtime/Taint;
    DUP2
    INVOKESTATIC edu/columbia/cs/psl/phosphor/struct/TaggedCharArray.unwrap (Ledu/columbia/cs/psl/phosphor/struct/TaggedCharArray;)[C
    PUTFIELD edu/columbia/cs/psl/test/phosphor/AutoTaintConstructorsObjTagITCase$ExampleWithSinkConstructors.cs : [C
    PUTFIELD edu/columbia/cs/psl/test/phosphor/AutoTaintConstructorsObjTagITCase$ExampleWithSinkConstructors.csPHOSPHOR_WRAPPER : Ledu/columbia/cs/psl/phosphor/struct/TaggedCharArray;
   L6
    LINENUMBER 39 L6
    ALOAD 3
    ILOAD 2
    INVOKEVIRTUAL edu/columbia/cs/psl/phosphor/runtime/PhosphorStackFrame.popStackFrameIfNeeded (Z)V
    GETSTATIC edu/columbia/cs/psl/phosphor/Configuration.autoTainter : Ledu/columbia/cs/psl/phosphor/runtime/TaintSourceWrapper;
    LDC "edu/columbia/cs/psl/test/phosphor/AutoTaintConstructorsObjTagITCase$ExampleWithSinkConstructors.<init>([C)V"
    LDC "edu/columbia/cs/psl/test/phosphor/AutoTaintConstructorsObjTagITCase$ExampleWithSinkConstructors.<init>([C)V"
    INVOKEVIRTUAL edu/columbia/cs/psl/phosphor/runtime/TaintSourceWrapper.exitingSink (Ljava/lang/String;Ljava/lang/String;)V
    RETURN
   L7
    LOCALVARIABLE this Ledu/columbia/cs/psl/test/phosphor/AutoTaintConstructorsObjTagITCase$ExampleWithSinkConstructors; L2 L7 0
    LOCALVARIABLE cs$$PHOSPHORTAG Ledu/columbia/cs/psl/phosphor/runtime/Taint; L1 L7 7
    LOCALVARIABLE this$$PHOSPHORTAG Ledu/columbia/cs/psl/phosphor/runtime/Taint; L0 L7 6
    LOCALVARIABLE cs [C L2 L7 1
    LOCALVARIABLE phosphorStackFrame Ledu/columbia/cs/psl/phosphor/runtime/PhosphorStackFrame; L2 L7 3
    LOCALVARIABLE phosphorStackFrameShouldBeClearedAtEnd Z L2 L7 2
    LOCALVARIABLE phosphorStackTaint0 Ledu/columbia/cs/psl/phosphor/runtime/Taint; L2 L7 4
    LOCALVARIABLE phosphorStackTaint1 Ledu/columbia/cs/psl/phosphor/runtime/Taint; L2 L7 5
   L4
   FRAME FULL [] [java/lang/Throwable]
    ASTORE 1
    GETSTATIC edu/columbia/cs/psl/phosphor/Configuration.autoTainter : Ledu/columbia/cs/psl/phosphor/runtime/TaintSourceWrapper;
    LDC "edu/columbia/cs/psl/test/phosphor/AutoTaintConstructorsObjTagITCase$ExampleWithSinkConstructors.<init>([C)V"
    LDC "edu/columbia/cs/psl/test/phosphor/AutoTaintConstructorsObjTagITCase$ExampleWithSinkConstructors.<init>([C)V"
    INVOKEVIRTUAL edu/columbia/cs/psl/phosphor/runtime/TaintSourceWrapper.exitingSink (Ljava/lang/String;Ljava/lang/String;)V
    ALOAD 1
    GETSTATIC edu/columbia/cs/psl/phosphor/Configuration.autoTainter : Ledu/columbia/cs/psl/phosphor/runtime/TaintSourceWrapper;
    LDC "edu/columbia/cs/psl/test/phosphor/AutoTaintConstructorsObjTagITCase$ExampleWithSinkConstructors.<init>([C)V"
    LDC "edu/columbia/cs/psl/test/phosphor/AutoTaintConstructorsObjTagITCase$ExampleWithSinkConstructors.<init>([C)V"
    INVOKEVIRTUAL edu/columbia/cs/psl/phosphor/runtime/TaintSourceWrapper.exitingSink (Ljava/lang/String;Ljava/lang/String;)V
    ATHROW
    MAXSTACK = 5
    MAXLOCALS = 8

  // access flags 0x1
  public <init>(C)V
    LDC -805359940
    INVOKESTATIC edu/columbia/cs/psl/phosphor/runtime/PhosphorStackFrame.forMethod (I)Ledu/columbia/cs/psl/phosphor/runtime/PhosphorStackFrame;
    DUP
    INVOKEVIRTUAL edu/columbia/cs/psl/phosphor/runtime/PhosphorStackFrame.getAndClearCleanupFlag ()Z
    ISTORE 2
    ASTORE 3
    INVOKESTATIC edu/columbia/cs/psl/phosphor/runtime/Taint.emptyTaint ()Ledu/columbia/cs/psl/phosphor/runtime/Taint;
    ASTORE 4
    INVOKESTATIC edu/columbia/cs/psl/phosphor/runtime/Taint.emptyTaint ()Ledu/columbia/cs/psl/phosphor/runtime/Taint;
    ASTORE 5
    ALOAD 3
    DUP
    ICONST_0
    INVOKEVIRTUAL edu/columbia/cs/psl/phosphor/runtime/PhosphorStackFrame.getArgTaint (I)Ledu/columbia/cs/psl/phosphor/runtime/Taint;
   L0
    INVOKESTATIC edu/columbia/cs/psl/phosphor/runtime/Taint.emptyTaint ()Ledu/columbia/cs/psl/phosphor/runtime/Taint;
    ASTORE 6
    ASTORE 6
    NOP
    DUP
    ICONST_1
    INVOKEVIRTUAL edu/columbia/cs/psl/phosphor/runtime/PhosphorStackFrame.getArgTaint (I)Ledu/columbia/cs/psl/phosphor/runtime/Taint;
   L1
    INVOKESTATIC edu/columbia/cs/psl/phosphor/runtime/Taint.emptyTaint ()Ledu/columbia/cs/psl/phosphor/runtime/Taint;
    ASTORE 7
    ASTORE 7
    LDC "PhosphorArgTaintIndices=6,7,"
    POP
    POP
   L2
    LINENUMBER 33 L2
    ALOAD 0
    ALOAD 6
    ASTORE 4
    ALOAD 3
    ALOAD 4
    ICONST_0
    INVOKEVIRTUAL edu/columbia/cs/psl/phosphor/runtime/PhosphorStackFrame.setArgTaint (Ledu/columbia/cs/psl/phosphor/runtime/Taint;I)V
    ALOAD 3
    LDC -857263373
    INVOKEVIRTUAL edu/columbia/cs/psl/phosphor/runtime/PhosphorStackFrame.prepareForCall (I)V
    INVOKESPECIAL java/lang/Object.<init> ()V
    GETSTATIC edu/columbia/cs/psl/phosphor/Configuration.autoTainter : Ledu/columbia/cs/psl/phosphor/runtime/TaintSourceWrapper;
    LDC "edu/columbia/cs/psl/test/phosphor/AutoTaintConstructorsObjTagITCase$ExampleWithSinkConstructors.<init>(C)V"
    LDC "edu/columbia/cs/psl/test/phosphor/AutoTaintConstructorsObjTagITCase$ExampleWithSinkConstructors.<init>(C)V"
    INVOKEVIRTUAL edu/columbia/cs/psl/phosphor/runtime/TaintSourceWrapper.enteringSink (Ljava/lang/String;Ljava/lang/String;)V
    GETSTATIC edu/columbia/cs/psl/phosphor/Configuration.autoTainter : Ledu/columbia/cs/psl/phosphor/runtime/TaintSourceWrapper;
    SIPUSH 2
    ANEWARRAY java/lang/Object
    DUP
    ICONST_0
    ALOAD 0
    AASTORE
    DUP
    ICONST_1
    ILOAD 1
    NEW java/lang/Character
    DUP_X1
    SWAP
    INVOKESPECIAL java/lang/Character.<init> (C)V
    AASTORE
    SIPUSH 2
    ANEWARRAY edu/columbia/cs/psl/phosphor/runtime/Taint
    DUP
    ICONST_0
    ALOAD 6
    AASTORE
    DUP
    ICONST_1
    ALOAD 7
    AASTORE
    LDC "edu/columbia/cs/psl/test/phosphor/AutoTaintConstructorsObjTagITCase$ExampleWithSinkConstructors.<init>(C)V"
    LDC "edu/columbia/cs/psl/test/phosphor/AutoTaintConstructorsObjTagITCase$ExampleWithSinkConstructors.<init>(C)V"
    INVOKEVIRTUAL edu/columbia/cs/psl/phosphor/runtime/TaintSourceWrapper.checkTaint ([Ljava/lang/Object;[Ledu/columbia/cs/psl/phosphor/runtime/Taint;Ljava/lang/String;Ljava/lang/String;)V
    TRYCATCHBLOCK L3 L4 L4 null
   L3
    ALOAD 3
    INVOKEVIRTUAL edu/columbia/cs/psl/phosphor/runtime/PhosphorStackFrame.getReturnTaint ()Ledu/columbia/cs/psl/phosphor/runtime/Taint;
    POP
   L5
    LINENUMBER 34 L5
    ALOAD 0
    ALOAD 6
    ASTORE 4
    ILOAD 1
    ALOAD 7
    ASTORE 5
    ALOAD 5
    DUP2_X1
    POP2
    DUP_X2
    SWAP
    PUTFIELD edu/columbia/cs/psl/test/phosphor/AutoTaintConstructorsObjTagITCase$ExampleWithSinkConstructors.cPHOSPHOR_TAG : Ledu/columbia/cs/psl/phosphor/runtime/Taint;
    PUTFIELD edu/columbia/cs/psl/test/phosphor/AutoTaintConstructorsObjTagITCase$ExampleWithSinkConstructors.c : C
   L6
    LINENUMBER 35 L6
    ALOAD 3
    ILOAD 2
    INVOKEVIRTUAL edu/columbia/cs/psl/phosphor/runtime/PhosphorStackFrame.popStackFrameIfNeeded (Z)V
    GETSTATIC edu/columbia/cs/psl/phosphor/Configuration.autoTainter : Ledu/columbia/cs/psl/phosphor/runtime/TaintSourceWrapper;
    LDC "edu/columbia/cs/psl/test/phosphor/AutoTaintConstructorsObjTagITCase$ExampleWithSinkConstructors.<init>(C)V"
    LDC "edu/columbia/cs/psl/test/phosphor/AutoTaintConstructorsObjTagITCase$ExampleWithSinkConstructors.<init>(C)V"
    INVOKEVIRTUAL edu/columbia/cs/psl/phosphor/runtime/TaintSourceWrapper.exitingSink (Ljava/lang/String;Ljava/lang/String;)V
    RETURN
   L7
    LOCALVARIABLE this Ledu/columbia/cs/psl/test/phosphor/AutoTaintConstructorsObjTagITCase$ExampleWithSinkConstructors; L2 L7 0
    LOCALVARIABLE this$$PHOSPHORTAG Ledu/columbia/cs/psl/phosphor/runtime/Taint; L0 L7 6
    LOCALVARIABLE c$$PHOSPHORTAG Ledu/columbia/cs/psl/phosphor/runtime/Taint; L1 L7 7
    LOCALVARIABLE c C L2 L7 1
    LOCALVARIABLE phosphorStackFrame Ledu/columbia/cs/psl/phosphor/runtime/PhosphorStackFrame; L2 L7 3
    LOCALVARIABLE phosphorStackFrameShouldBeClearedAtEnd Z L2 L7 2
    LOCALVARIABLE phosphorStackTaint0 Ledu/columbia/cs/psl/phosphor/runtime/Taint; L2 L7 4
    LOCALVARIABLE phosphorStackTaint1 Ledu/columbia/cs/psl/phosphor/runtime/Taint; L2 L7 5
   L4
   FRAME FULL [] [java/lang/Throwable]
    ASTORE 1
    GETSTATIC edu/columbia/cs/psl/phosphor/Configuration.autoTainter : Ledu/columbia/cs/psl/phosphor/runtime/TaintSourceWrapper;
    LDC "edu/columbia/cs/psl/test/phosphor/AutoTaintConstructorsObjTagITCase$ExampleWithSinkConstructors.<init>(C)V"
    LDC "edu/columbia/cs/psl/test/phosphor/AutoTaintConstructorsObjTagITCase$ExampleWithSinkConstructors.<init>(C)V"
    INVOKEVIRTUAL edu/columbia/cs/psl/phosphor/runtime/TaintSourceWrapper.exitingSink (Ljava/lang/String;Ljava/lang/String;)V
    ALOAD 1
    GETSTATIC edu/columbia/cs/psl/phosphor/Configuration.autoTainter : Ledu/columbia/cs/psl/phosphor/runtime/TaintSourceWrapper;
    LDC "edu/columbia/cs/psl/test/phosphor/AutoTaintConstructorsObjTagITCase$ExampleWithSinkConstructors.<init>(C)V"
    LDC "edu/columbia/cs/psl/test/phosphor/AutoTaintConstructorsObjTagITCase$ExampleWithSinkConstructors.<init>(C)V"
    INVOKEVIRTUAL edu/columbia/cs/psl/phosphor/runtime/TaintSourceWrapper.exitingSink (Ljava/lang/String;Ljava/lang/String;)V
    ATHROW
    MAXSTACK = 5
    MAXLOCALS = 8

  // access flags 0x8
  static <clinit>()V
    LDC Ledu/columbia/cs/psl/test/phosphor/AutoTaintConstructorsObjTagITCase$ExampleWithSinkConstructors;.class
    INVOKESTATIC edu/columbia/cs/psl/phosphor/SourceSinkTransformer.retransform (Ljava/lang/Class;)V
    RETURN
    MAXSTACK = 1
    MAXLOCALS = 0

  // access flags 0x1001
  public synthetic getPHOSPHOR_TAG()Ljava/lang/Object;
    ALOAD 0
    GETFIELD edu/columbia/cs/psl/test/phosphor/AutoTaintConstructorsObjTagITCase$ExampleWithSinkConstructors.PHOSPHOR_TAG : Ledu/columbia/cs/psl/phosphor/runtime/Taint;
    ARETURN
    MAXSTACK = 1
    MAXLOCALS = 1

  // access flags 0x1001
  public synthetic setPHOSPHOR_TAG(Ljava/lang/Object;)V
    ALOAD 0
    ALOAD 1
    CHECKCAST edu/columbia/cs/psl/phosphor/runtime/Taint
    PUTFIELD edu/columbia/cs/psl/test/phosphor/AutoTaintConstructorsObjTagITCase$ExampleWithSinkConstructors.PHOSPHOR_TAG : Ledu/columbia/cs/psl/phosphor/runtime/Taint;
    RETURN
    MAXSTACK = 2
    MAXLOCALS = 2
}
